img_dice/__init__.py
img_dice/cli.py
img_dice/gui.py
img_dice/lib.py
img_dice/resources/form.ui
img_dice/resources/img-dice-social.png
img_dice/resources/img-dice.ico
img_dice/resources/img-dice.png
img_dice-0.3.0.dist-info/entry_points.txt
img_dice-0.3.0.dist-info/WHEEL
img_dice-0.3.0.dist-info/METADATA
img_dice-0.3.0.dist-info/RECORD
